korgalore/__init__.py
korgalore/cli.py
korgalore/gmail_target.py
korgalore/imap_target.py
korgalore/jmap_target.py
korgalore/lei_feed.py
korgalore/lore_feed.py
korgalore/maildir_target.py
korgalore/pi_feed.py
korgalore-0.2.2.dist-info/licenses/COPYING
korgalore-0.2.2.dist-info/METADATA
korgalore-0.2.2.dist-info/WHEEL
korgalore-0.2.2.dist-info/entry_points.txt
korgalore-0.2.2.dist-info/top_level.txt
korgalore-0.2.2.dist-info/RECORD
