Metadata-Version: 2.4
Name: korgalore
Version: 0.2.2
Summary: A tool to put public-inbox messages into your Gmail inbox.
Author-email: Konstantin Ryabitsev <konstantin@linuxfoundation.org>
License:                     GNU GENERAL PUBLIC LICENSE
Project-URL: Homepage, https://git.kernel.org/pub/scm/utils/korgalore/korgalore.git/
Project-URL: Repository, https://git.kernel.org/pub/scm/utils/korgalore/korgalore.git
Keywords: gmail,cli,email,google-api,lore.kernel.org,public-inbox
Classifier: Intended Audience :: Developers
Classifier: Development Status :: 3 - Alpha
Classifier: License :: OSI Approved :: GNU General Public License v2 or later (GPLv2+)
Classifier: Programming Language :: Python :: 3
Classifier: Programming Language :: Python :: 3.11
Classifier: Programming Language :: Python :: 3.12
Classifier: Programming Language :: Python :: 3.13
Classifier: Programming Language :: Python :: 3.14
Requires-Python: >=3.11
License-File: COPYING
Requires-Dist: google-auth>=2.0.0
Requires-Dist: google-auth-oauthlib>=1.0.0
Requires-Dist: google-auth-httplib2>=0.1.0
Requires-Dist: google-api-python-client>=2.0.0
Requires-Dist: click>=8.3.0
Requires-Dist: click-log>=0.4.0
Provides-Extra: dev
Requires-Dist: pytest>=7.0.0; extra == "dev"
Requires-Dist: mypy>=1.0.0; extra == "dev"
Dynamic: license-file
